sanskrit_transliteration/__init__.py
sanskrit_transliteration/__main__.py
sanskrit_transliteration/from_skt.py
sanskrit_transliteration/hk_and_skt.py
sanskrit_transliteration/utils.py
sanskrit_transliteration/velthius_and_hk.py
sanskrit_transliteration/velthius_and_skt.py
sanskrit_transliteration/wx_slp1.py
sanskrit_transliteration/wx_slp1_hk.py
sanskrit_transliteration/wx_slp1_skt.py
sanskrit_transliteration/wx_slp1_vel.py
sanskrit_transliteration-1.0.0.dist-info/entry_points.txt
sanskrit_transliteration-1.0.0.dist-info/METADATA
sanskrit_transliteration-1.0.0.dist-info/WHEEL
sanskrit_transliteration-1.0.0.dist-info/RECORD
