Metadata-Version: 2.1
Name: sanskrit-transliteration
Version: 1.0.0
Summary: To transliterate Sanskrit strings
Home-page: https://github.com/eadaradhiraj/Sanskrit-Transliteration
License: MIT
Author: Dhiraj Eadara
Author-email: eadaradhiraj@gmail.com
Requires-Python: >=3.7,<4.0
Classifier: License :: OSI Approved :: MIT License
Classifier: Programming Language :: Python :: 3
Classifier: Programming Language :: Python :: 3.7
Classifier: Programming Language :: Python :: 3.8
Classifier: Programming Language :: Python :: 3.9
Classifier: Programming Language :: Python :: 3.10
Classifier: Programming Language :: Python :: 3.11
Project-URL: Repository, https://github.com/eadaradhiraj/Sanskrit-Transliteration
